is_num/__init__.py
is_num/_version.py
is_num/is_num.py
is_num-0.0.2.dist-info/LICENSE
is_num-0.0.2.dist-info/METADATA
is_num-0.0.2.dist-info/WHEEL
is_num-0.0.2.dist-info/top_level.txt
is_num-0.0.2.dist-info/RECORD
