Metadata-Version: 2.1
Name: is-num
Version: 0.0.2
Summary: A Python library to determine if something is a num.
Home-page: UNKNOWN
Author: Mark Yang
Author-email: mark.xc.yang@gmail.com
License: UNKNOWN
Platform: UNKNOWN
Classifier: Programming Language :: Python :: 3
Classifier: License :: OSI Approved :: MIT License
Classifier: Operating System :: OS Independent
Requires-Python: >=3.7
